<meta>
	<info author="ber#8813" />
	<script src="replace.lua" type="client" />
	<file src="assets/txd/411.txd" />
	<file src="assets/txd/411.dff" />
	<file src="assets/txd/541.txd" />
	<file src="assets/txd/541.dff" />
	<file src="assets/txd/429.txd" />
	<file src="assets/txd/429.dff" />
	<file src="assets/txd/415.txd" />
	<file src="assets/txd/415.dff" />
	<file src="assets/txd/422.txd" />
	<file src="assets/txd/422.dff" />
	<file src="assets/txd/477.txd" />
	<file src="assets/txd/477.dff" />
	<file src="assets/txd/559.txd" />
	<file src="assets/txd/559.dff" />
	<file src="assets/txd/402.txd" />
	<file src="assets/txd/402.dff" />
	<file src="assets/txd/458.txd" />
	<file src="assets/txd/458.dff" />
	<file src="assets/txd/566.txd" />
	<file src="assets/txd/566.dff" />
	<file src="assets/txd/579.txd" />
	<file src="assets/txd/579.dff" />
	<file src="assets/txd/404.txd" />
	<file src="assets/txd/404.dff" />
	<file src="assets/txd/560.txd" />
	<file src="assets/txd/560.dff" />
	<file src="assets/txd/400.txd" />
	<file src="assets/txd/400.dff" />
	<file src="assets/txd/479.txd" />
	<file src="assets/txd/479.dff" />
	<file src="assets/txd/561.txd" />
	<file src="assets/txd/561.dff" />
	<file src="assets/txd/426.txd" />
	<file src="assets/txd/426.dff" />
	<file src="assets/txd/517.txd" />
	<file src="assets/txd/517.dff" />
	<file src="assets/txd/550.txd" />
	<file src="assets/txd/550.dff" />
	<file src="assets/txd/475.txd" />
	<file src="assets/txd/475.dff" />
	<file src="assets/txd/496.txd" />
	<file src="assets/txd/496.dff" />
	<file src="assets/txd/565.txd" />
	<file src="assets/txd/565.dff" />
	<file src="assets/txd/529.txd" />
	<file src="assets/txd/529.dff" />
	<file src="assets/txd/474.txd" />
	<file src="assets/txd/474.dff" />
	<file src="assets/txd/551.txd" />
	<file src="assets/txd/551.dff" />
	<file src="assets/txd/445.txd" />
	<file src="assets/txd/445.dff" />
	<file src="assets/txd/585.txd" />
	<file src="assets/txd/585.dff" />
	<file src="assets/txd/410.txd" />
	<file src="assets/txd/410.dff" />
	<file src="assets/txd/545.txd" />
	<file src="assets/txd/545.dff" />
	<file src="assets/txd/589.txd" />
	<file src="assets/txd/589.dff" />
	<file src="assets/txd/507.txd" />
	<file src="assets/txd/507.dff" />
	<file src="assets/txd/581.txd" />
	<file src="assets/txd/581.dff" />
	<file src="assets/txd/462.txd" />
	<file src="assets/txd/462.dff" />
	<file src="assets/txd/521.txd" />
	<file src="assets/txd/521.dff" />
	<file src="assets/txd/463.txd" />
	<file src="assets/txd/463.dff" />
	<file src="assets/txd/522.txd" />
	<file src="assets/txd/522.dff" />
	<file src="assets/txd/461.txd" />
	<file src="assets/txd/461.dff" />
	<file src="assets/txd/468.txd" />
	<file src="assets/txd/468.dff" />
	<file src="assets/txd/586.txd" />
	<file src="assets/txd/586.dff" />
	<file src="assets/txd/416.txd" />
	<file src="assets/txd/416.dff" />
	<file src="assets/txd/525.txd" />
	<file src="assets/txd/525.dff" />
	<file src="assets/txd/578.txd" />
	<file src="assets/txd/578.dff" />
</meta>